[
    {
        "username" : "",
        "firstname" : "",
        "last name" : "",
        "posts" : [],
        "totallikes" : ""
    },
    {
        "username" : "@matthew",
        "firstname" : "matthew",
        "last name" : "ong",
        "posts" : [],
        "totallikes" : "47"
    },
    {
        "username" : "@mjasmine",
        "firstname" : "jasmine",
        "last name" : "gayamo",
        "posts" : [],
        "totallikes" : "57"
    },
    {
        "username" : "@jannah",
        "firstname" : "jannah",
        "last name" : "facultad",
        "posts" : [],
        "totallikes" : "27"
    }
]